pyplotbrookings/.DS_Store
pyplotbrookings/__init__.py
pyplotbrookings/pyplotbrookings.py
pyplotbrookings/.ipynb_checkpoints/Examples-checkpoint.ipynb
pyplotbrookings/fonts/Helvetica/readme.html
pyplotbrookings/fonts/Helvetica/Helvetica Black Condensed/Helvetica Black Condensed.otf
pyplotbrookings/fonts/Helvetica/Helvetica Black Condensed Oblique/Helvetica Black Condensed Oblique.otf
pyplotbrookings/fonts/Helvetica/Helvetica Bold Condensed/Helvetica Bold Condensed.otf
pyplotbrookings/fonts/Helvetica/Helvetica Bold Condensed Oblique/Helvetica Bold Condensed Oblique.otf
pyplotbrookings/fonts/Helvetica/Helvetica Bold Italic/Helvetica Bold Italic.ttf
pyplotbrookings/fonts/Helvetica/Helvetica Bold Narrow Oblique/Helvetica Bold Narrow Oblique.otf
pyplotbrookings/fonts/Helvetica/Helvetica BoldOblique/Helvetica BoldOblique.ttf
pyplotbrookings/fonts/Helvetica/Helvetica CE Bold/Helvetica CE Bold.otf
pyplotbrookings/fonts/Helvetica/Helvetica CE Bold Condensed/Helvetica CE Bold Condensed.otf
pyplotbrookings/fonts/Helvetica/Helvetica CE Bold Condensed Oblique/Helvetica CE Bold Condensed Oblique.otf
pyplotbrookings/fonts/Helvetica/Helvetica CE Bold Narrow/Helvetica CE Bold Narrow.otf
pyplotbrookings/fonts/Helvetica/Helvetica CE Bold Narrow Oblique/Helvetica CE Bold Narrow Oblique.otf
pyplotbrookings/fonts/Helvetica/Helvetica CE Bold Oblique/Helvetica CE Bold Oblique.otf
pyplotbrookings/fonts/Helvetica/Helvetica CE Condensed Oblique/Helvetica CE Condensed Oblique.otf
pyplotbrookings/fonts/Helvetica/Helvetica CE Medium/Helvetica CE Medium.otf
pyplotbrookings/fonts/Helvetica/Helvetica CE Medium Condensed/Helvetica CE Medium Condensed.otf
pyplotbrookings/fonts/Helvetica/Helvetica CE Narrow/Helvetica CE Narrow.otf
pyplotbrookings/fonts/Helvetica/Helvetica CE Narrow Oblique/Helvetica CE Narrow Oblique.otf
pyplotbrookings/fonts/Helvetica/Helvetica CE Oblique/Helvetica CE Oblique.otf
pyplotbrookings/fonts/Helvetica/Helvetica Condensed Oblique/Helvetica Condensed Oblique.otf
pyplotbrookings-0.2.1.dist-info/METADATA
pyplotbrookings-0.2.1.dist-info/WHEEL
pyplotbrookings-0.2.1.dist-info/licenses/LICENSE
pyplotbrookings-0.2.1.dist-info/RECORD
