Metadata-Version: 2.1
Name: pyplotbrookings
Version: 0.2.1
Summary: A plotting package for the Brookings Institution
Project-URL: Homepage, https://github.com/Adam-Sedlak-Brookings/pyplotbrookings
Author-email: Adam Sedlak <asedlak@brookings.edu>
License-File: LICENSE
Classifier: License :: OSI Approved :: MIT License
Classifier: Operating System :: OS Independent
Classifier: Programming Language :: Python :: 3
Requires-Python: >=3.7
